LICENSE
MANIFEST.in
README.rst
setup.cfg
setup.py
versioneer.py
tests/__init__.py
tests/test_general.py
tpRigToolkit/__init__.py
tpRigToolkit/tools/__init__.py
tpRigToolkit/tools/interpolateit/__init__.py
tpRigToolkit/tools/interpolateit/__logging__.ini
tpRigToolkit/tools/interpolateit/__version__.py
tpRigToolkit/tools/interpolateit/_version.py
tpRigToolkit/tools/interpolateit/core/__init__.py
tpRigToolkit/tools/interpolateit/core/client.py
tpRigToolkit/tools/interpolateit/core/consts.py
tpRigToolkit/tools/interpolateit/core/controller.py
tpRigToolkit/tools/interpolateit/core/model.py
tpRigToolkit/tools/interpolateit/core/tool.py
tpRigToolkit/tools/interpolateit/core/toolset.py
tpRigToolkit/tools/interpolateit/core/view.py
tpRigToolkit/tools/interpolateit/dccs/__init__.py
tpRigToolkit/tools/interpolateit/dccs/max/__init__.py
tpRigToolkit/tools/interpolateit/dccs/max/server.py
tpRigToolkit/tools/interpolateit/dccs/maya/__init__.py
tpRigToolkit/tools/interpolateit/dccs/maya/server.py
tpRigToolkit/tools/interpolateit/widgets/__init__.py
tpRigToolkit/tools/interpolateit/widgets/interpolator.py
tpRigToolkit_tools_interpolateit.egg-info/PKG-INFO
tpRigToolkit_tools_interpolateit.egg-info/SOURCES.txt
tpRigToolkit_tools_interpolateit.egg-info/dependency_links.txt
tpRigToolkit_tools_interpolateit.egg-info/not-zip-safe
tpRigToolkit_tools_interpolateit.egg-info/requires.txt
tpRigToolkit_tools_interpolateit.egg-info/top_level.txt