Metadata-Version: 2.1
Name: tpRigToolkit-tools-interpolateit
Version: 0.0.2
Summary: Tool to store/blend interpolate states of objects
Home-page: https://github.com/tpRigToolkit/tpRigToolkit-tools-interpolateit
Author: Tomas Poveda
Author-email: tpovedatd@gmail.com
License: MIT
Platform: UNKNOWN
Provides-Extra: dev
Provides-Extra: test
